rektor/__init__.py
rektor/__main__.py
rektor/main.py
rektor/merkle_proof.py
rektor/util.py
rektor-4.0.0.dist-info/LICENSE
rektor-4.0.0.dist-info/METADATA
rektor-4.0.0.dist-info/WHEEL
rektor-4.0.0.dist-info/RECORD
