Metadata-Version: 2.1
Name: rektor
Version: 4.0.0
Summary: Rekor Transparency Log Verifier
Author: Adnan Jakati
Author-email: mj3184@nyu.edu
Requires-Python: >=3.12,<4.0
Classifier: Programming Language :: Python :: 3
Classifier: Programming Language :: Python :: 3.12
Classifier: Programming Language :: Python :: 3.13
Requires-Dist: cryptography (>=43.0.3,<44.0.0)
Requires-Dist: mypy (>=1.11,<2.0)
Requires-Dist: requests (>=2.32.3,<3.0.0)
